COPYING
MANIFEST.in
README.rst
fakenewsredis.py
setup.cfg
setup.py
fakenewsredis.egg-info/PKG-INFO
fakenewsredis.egg-info/SOURCES.txt
fakenewsredis.egg-info/dependency_links.txt
fakenewsredis.egg-info/requires.txt
fakenewsredis.egg-info/top_level.txt