Metadata-Version: 2.1
Name: fakenewsredis
Version: 0.10.1
Summary: Fake implementation of redis API for testing purposes (DEPRECATED: use fakeredis).
Home-page: https://github.com/ska-sa/fakenewsredis
Author: James Saryerwinnie
Author-email: js@jamesls.com
Maintainer: Bruce Merry
Maintainer-email: bmerry@ska.ac.za
License: BSD
Platform: UNKNOWN
Classifier: Development Status :: 7 - Inactive
Classifier: License :: OSI Approved :: BSD License
Classifier: Programming Language :: Python :: 2
Classifier: Programming Language :: Python :: 2.6
Classifier: Programming Language :: Python :: 2.7
Classifier: Programming Language :: Python :: 3
Classifier: Programming Language :: Python :: 3.3
Classifier: Programming Language :: Python :: 3.4
Classifier: Programming Language :: Python :: 3.5
Classifier: Programming Language :: Python :: 3.6
Provides-Extra: lua
